image_archive_viewer/__init__.py
image_archive_viewer/archive_reader.py
image_archive_viewer/logging_setup.py
image_archive_viewer/viewer.py
image_archive_viewer-0.4.1.dist-info/METADATA
image_archive_viewer-0.4.1.dist-info/WHEEL
image_archive_viewer-0.4.1.dist-info/entry_points.txt
image_archive_viewer-0.4.1.dist-info/licenses/LICENSE
image_archive_viewer-0.4.1.dist-info/RECORD
