Metadata-Version: 2.4
Name: image-archive-viewer
Version: 0.4.1
Summary: ComicView: an image archive (ZIP, RAR, CBR, CBZ) viewer written in Python and Qt
Project-URL: homepage, https://github.com/CaptSolo/image-archive-viewer/
Author: CaptSolo
License: MIT
License-File: LICENSE
Keywords: Image viewer,Qt,ZIP archives
Classifier: License :: OSI Approved :: MIT License
Classifier: Operating System :: OS Independent
Classifier: Programming Language :: Python :: 3
Classifier: Programming Language :: Python :: 3.8
Classifier: Programming Language :: Python :: 3.9
Classifier: Programming Language :: Python :: 3.10
Classifier: Programming Language :: Python :: 3.11
Classifier: Programming Language :: Python :: 3.12
Classifier: Programming Language :: Python :: 3.13
Requires-Python: >=3.8
Requires-Dist: pillow
Requires-Dist: pyqt5
Requires-Dist: rarfile
Provides-Extra: test
Requires-Dist: pytest-cov>=4.0; extra == 'test'
Requires-Dist: pytest-qt>=4.0; extra == 'test'
Requires-Dist: pytest>=7.0; extra == 'test'
